PromptTasker/__init__.py
PromptTasker/backend.py
PromptTasker/cli.py
prompttasker-0.1.9.dist-info/METADATA
prompttasker-0.1.9.dist-info/WHEEL
prompttasker-0.1.9.dist-info/entry_points.txt
prompttasker-0.1.9.dist-info/top_level.txt
prompttasker-0.1.9.dist-info/RECORD
