Metadata-Version: 2.4
Name: PromptTasker
Version: 0.1.9
Summary: A prompt-powered multi-task CLI utility
Author: Suneha Datta
Requires-Python: >=3.7
Requires-Dist: requests
Requires-Dist: numpy
Requires-Dist: pandas
Requires-Dist: pillow
Requires-Dist: duckdb
Requires-Dist: mdformat
Dynamic: author
Dynamic: description
Dynamic: description-content-type
Dynamic: requires-dist
Dynamic: requires-python
Dynamic: summary
